<?xml version="1.0" encoding="UTF-8"?>
<codex>
	<head>
		<type>manuscript</type>
		<shortid>borghlat359</shortid>
		<title>Vatican City, Biblioteca Apostolica Vaticana, borgh. lat. 359</title>
	  <initial>B</initial>
	  <!-- contains part of Alexander of Hales Summa Halensis -->
		<hasItems>
			<item>
				<canonical>true</canonical>
			  <shortid>borghlat359/item1</shortid>
			  <canvasBase>http://digi.vatlib.it/iiif/MSS_Borgh.359/canvas/</canvasBase>
			  <manifestOfficial>http://digi.vatlib.it/iiif/MSS_Borgh.359/manifest.json</manifestOfficial>
			</item>
		</hasItems>
	</head>
	<surfaces>
	</surfaces>
</codex>
